logkeeper_py-1.0.3.dist-info/METADATA
logkeeper_py-1.0.3.dist-info/WHEEL
logkeeper_py-1.0.3.dist-info/licenses/LICENSE
logkeeper_py/__init__.py
logkeeper_py/__init__.pyi
logkeeper_py/logkeeper_py.cp314-win_amd64.pyd
logkeeper_py/py.typed
logkeeper_py-1.0.3.dist-info/RECORD
