Metadata-Version: 2.4
Name: logkeeper_py
Version: 1.0.3
Classifier: Programming Language :: Python :: 3
Classifier: Programming Language :: Python :: 3.9
Classifier: Programming Language :: Python :: 3.10
Classifier: Programming Language :: Python :: 3.11
Classifier: Programming Language :: Python :: 3.12
Classifier: Programming Language :: Python :: 3.13
Classifier: Programming Language :: Python :: 3.14
Classifier: Programming Language :: Rust
Classifier: Programming Language :: Python :: Implementation :: CPython
Classifier: License :: OSI Approved :: MIT License
Classifier: Topic :: System :: Logging
Classifier: Topic :: Software Development :: Libraries :: Python Modules
Classifier: Intended Audience :: Developers
Classifier: Development Status :: 5 - Production/Stable
Classifier: Operating System :: OS Independent
Classifier: Typing :: Typed
License-File: LICENSE
Summary: Simple file logger that works out of the box with automatic timestamping and session management
Author-email: Raul Catalinas Esteban <raulcatalinas@gmail.com>
Requires-Python: >=3.9
Project-URL: Homepage, https://github.com/RaulCatalinas/LogKeeper-Python
Project-URL: Repository, https://github.com/RaulCatalinas/LogKeeper-Python
Project-URL: Issues, https://github.com/RaulCatalinas/LogKeeper-Python/issues
Project-URL: Changelog, https://github.com/RaulCatalinas/LogKeeper-Python/blob/main/CHANGELOG.md
